{"Adult":false,"Backdrop_Path":"/1fPBbfrl9KfQ9W5VOqPT4Wc07ZA.jpg","Budget":5000000,"Genres":[{"Id":12,"Name":"Adventure"},{"Id":10751,"Name":"Family"}],"Id":18444,"Imdb_Id":"tt0054357","Original_Title":"Swiss Family Robinson","Overview":"After being shipwrecked, the Robinson family is marooned on an island inhabited only by an impressive array of wildlife. In true pioneer spirit, they quickly make themselves at home but soon face a danger even greater than nature: dastardly pirates. A rousing adventure suitable for the whole family, this Disney adaptation of the classic Johann Wyss novel stars Dorothy McGuire and John Mills as Mother and Father Robinson.","Popularity":10.147,"Poster_Path":"/jj2Pkkgrasm4A5AUqXwpJhb5VX3.jpg","Production_Companies":[{"Name":"Walt Disney Productions","Id":3166}],"Production_Countries":[{"Iso_3166_1":"US","Name":"United States of America"}],"Release_Date":"1960-12-21","Revenue":40356000,"Runtime":126,"Spoken_Languages":[{"Iso_639_1":"en","Name":"English"},{"Iso_639_1":"it","Name":"Italiano"}],"Status":"Released","Tagline":"THE ADVENTURE OF ADVENTURES!","Title":"Swiss Family Robinson","Vote_Average":7.1,"Vote_Count":152,"Casts":{"Cast":[{"Id":11859,"Name":"John Mills","Character":"Father","Order":0,"Cast_Id":8,"Profile_Path":"/jMqhI1NeTwgdKsrj9vMshk1r5hP.jpg"},{"Id":24815,"Name":"Dorothy McGuire","Character":"Mother","Order":1,"Cast_Id":9,"Profile_Path":"/ilzwbgMD8rHZ1wNKI4Roi4GNrGi.jpg"},{"Id":83128,"Name":"James MacArthur","Character":"Fritz","Order":2,"Cast_Id":10,"Profile_Path":"/t2DzrPh00QuOrCbdYzK4SggeG9H.jpg"},{"Id":83129,"Name":"Janet Munro","Character":"Roberta 'Bertie'","Order":3,"Cast_Id":11,"Profile_Path":"/ydXF8J88QDvCSSMMCVDg5Cz2snB.jpg"},{"Id":12249,"Name":"Sessue Hayakawa","Character":"Kuala, Pirate Chief","Order":4,"Cast_Id":12,"Profile_Path":"/LLtMGKvp3k4LiesKdUwXhugEfE.jpg"},{"Id":83130,"Name":"Tommy Kirk","Character":"Ernst","Order":5,"Cast_Id":14,"Profile_Path":"/30E79Tjibru53EWmXNmAddZSKlx.jpg"},{"Id":83131,"Name":"Kevin Corcoran","Character":"Francis","Order":6,"Cast_Id":13,"Profile_Path":"/3RLdYK6I0JNqDf5FtAG4EFPzy5f.jpg"},{"Id":14300,"Name":"Cecil Parker","Character":"Captain Moreland","Order":7,"Cast_Id":15,"Profile_Path":"/62aOulE64RjUEDWAVqJeWMS9JM3.jpg"},{"Id":83132,"Name":"Andy Ho","Character":"Auban","Order":8,"Cast_Id":16},{"Id":83133,"Name":"Milton Reid","Character":"Big Pirate","Order":9,"Cast_Id":17},{"Id":83134,"Name":"Larry Taylor","Character":"Pirate","Order":10,"Cast_Id":18,"Profile_Path":"/p7OgTXIo07bn81yTSGb3CBsMWlZ.jpg"}],"Crew":[{"Id":2106,"Credit_Id":"52fe477d9251416c7509b3a1","Name":"Walt Disney","Department":"Production","Job":"Producer","Profile_Path":"/mrcVG49U2PVm1LpPMmwBtn5ZzOh.jpg"},{"Id":10221,"Credit_Id":"52fe477d9251416c7509b403","Name":"Julie Harris","Department":"Costume & Make-Up","Job":"Costume Design","Profile_Path":"/3GkMIV0cb3373xxd5eDba43T909.jpg"},{"Id":10614,"Credit_Id":"52fe477d9251416c7509b3fd","Name":"Jack Stephens","Department":"Art","Job":"Set Decoration"},{"Id":25823,"Credit_Id":"52fe477d9251416c7509b3f1","Name":"Peter Boita","Department":"Editing","Job":"Editor"},{"Id":35318,"Credit_Id":"52fe477d9251416c7509b3a7","Name":"Ken Annakin","Department":"Directing","Job":"Director","Profile_Path":"/8oFZguwvvd1F3CETULi37Gq1ZtL.jpg"},{"Id":39054,"Credit_Id":"52fe477d9251416c7509b3e5","Name":"William Alwyn","Department":"Sound","Job":"Original Music Composer"},{"Id":40356,"Credit_Id":"52fe477d9251416c7509b3f7","Name":"John Howell","Department":"Art","Job":"Production Design"},{"Id":49962,"Credit_Id":"52fe477d9251416c7509b395","Name":"Bill Anderson","Department":"Production","Job":"Producer"},{"Id":83124,"Credit_Id":"52fe477d9251416c7509b39b","Name":"Basil Keys","Department":"Production","Job":"Producer"},{"Id":83126,"Credit_Id":"52fe477d9251416c7509b3ad","Name":"Lowell S. Hawley","Department":"Writing","Job":"Screenplay"},{"Id":83127,"Credit_Id":"52fe477d9251416c7509b3b3","Name":"Johann David Wyss","Department":"Writing","Job":"Author"},{"Id":83135,"Credit_Id":"52fe477d9251416c7509b3eb","Name":"Harry Waxman","Department":"Camera","Job":"Director of Photography"}]},"Releases":{"Countries":[{"Iso_3166_1":"SE","Certification":"11","Release_Date":"1962-02-22T00:00:00.0000000Z"},{"Iso_3166_1":"DE","Certification":"6","Release_Date":"1965-01-29T00:00:00.0000000Z"},{"Iso_3166_1":"NL","Certification":"6","Release_Date":"2007-01-03T00:00:00.0000000Z"},{"Iso_3166_1":"US","Certification":"G","Release_Date":"1960-12-21T00:00:00.0000000Z"},{"Iso_3166_1":"AU","Certification":"G","Release_Date":"1961-08-17T00:00:00.0000000Z"},{"Iso_3166_1":"GB","Certification":"U","Release_Date":"1960-12-21T00:00:00.0000000Z"}]},"Images":{"Backdrops":[{"Aspect_Ratio":1.77072538860104,"File_Path":"/1fPBbfrl9KfQ9W5VOqPT4Wc07ZA.jpg","Height":772,"Vote_Average":5.3125,"Vote_Count":1,"Width":1367},{"Aspect_Ratio":1.77777777777778,"File_Path":"/xzOcOUiASg2aIt6LJWY0SCjiWfQ.jpg","Height":1080,"Vote_Average":5.246,"Vote_Count":2,"Width":1920},{"Aspect_Ratio":1.77777777777778,"File_Path":"/otYehfQhCa13jXhgc7x65ecEb2.jpg","Height":1080,"Iso_639_1":"da","Vote_Average":0,"Vote_Count":0,"Width":1920},{"Aspect_Ratio":1.77777777777778,"File_Path":"/vNijAksUUekLP0sMuuGctkSFK2L.jpg","Height":1080,"Vote_Average":0,"Vote_Count":0,"Width":1920},{"Aspect_Ratio":1.77777777777778,"File_Path":"/gzhg4V6n2EV0bjuckiCzAjVcYUq.jpg","Height":1080,"Iso_639_1":"en","Vote_Average":0,"Vote_Count":0,"Width":1920},{"Aspect_Ratio":1.77777777777778,"File_Path":"/cYI0UtOSY8hvRT82FyCM0fkXow4.jpg","Height":1080,"Vote_Average":0,"Vote_Count":0,"Width":1920},{"Aspect_Ratio":1.77777777777778,"File_Path":"/vrE2wsaW95X0svez7x6ucM4ifOh.jpg","Height":1080,"Vote_Average":0,"Vote_Count":0,"Width":1920}],"Posters":[{"Aspect_Ratio":0.666666666666667,"File_Path":"/bCyD8X13Zr8kDyTmAjukS1t84vb.jpg","Height":1200,"Iso_639_1":"fr","Vote_Average":5.384,"Vote_Count":2,"Width":800},{"Aspect_Ratio":0.666666666666667,"File_Path":"/iE8TuQZd3HrU1k177CWMCn57aPU.jpg","Height":1200,"Iso_639_1":"de","Vote_Average":5.384,"Vote_Count":2,"Width":800},{"Aspect_Ratio":0.666666666666667,"File_Path":"/iJsOl4Yps2vWDwRaPguXHhFCORI.jpg","Height":1500,"Iso_639_1":"sv","Vote_Average":5.312,"Vote_Count":1,"Width":1000},{"Aspect_Ratio":0.666666666666667,"File_Path":"/jFlk2dOAnK8fziGvUkf2QI19Lwc.jpg","Height":1500,"Iso_639_1":"fr","Vote_Average":5.312,"Vote_Count":1,"Width":1000},{"Aspect_Ratio":0.666666666666667,"File_Path":"/AgnApwavpxAgA7NTkg0fWEkVPUH.jpg","Height":1200,"Iso_639_1":"de","Vote_Average":5.312,"Vote_Count":1,"Width":800},{"Aspect_Ratio":0.673333333333333,"File_Path":"/bfK4Upz764gcbu0QywoeX8vQljs.jpg","Height":1200,"Iso_639_1":"es","Vote_Average":5.312,"Vote_Count":1,"Width":808},{"Aspect_Ratio":0.666666666666667,"File_Path":"/jj2Pkkgrasm4A5AUqXwpJhb5VX3.jpg","Height":1500,"Iso_639_1":"en","Vote_Average":5.28,"Vote_Count":16,"Width":1000},{"Aspect_Ratio":0.666666666666667,"File_Path":"/9zwsyHGfpIK8oRnFnnkbDZPvKU8.jpg","Height":1500,"Iso_639_1":"en","Vote_Average":5.258,"Vote_Count":6,"Width":1000},{"Aspect_Ratio":0.666666666666667,"File_Path":"/3ZItm1RcdwNuPnCaaqEFGrbVlcO.jpg","Height":3000,"Iso_639_1":"en","Vote_Average":5.246,"Vote_Count":2,"Width":2000},{"Aspect_Ratio":0.700902151283831,"File_Path":"/eKI5rHtJG05TJ8UBJ9DVJhfkG1S.jpg","Height":1441,"Iso_639_1":"es","Vote_Average":5.246,"Vote_Count":2,"Width":1010},{"Aspect_Ratio":0.666666666666667,"File_Path":"/zoKiSaC8PmoOgouZrjw1hPpOjY1.jpg","Height":1500,"Iso_639_1":"en","Vote_Average":5.206,"Vote_Count":12,"Width":1000},{"Aspect_Ratio":0.657769304099142,"File_Path":"/qqTnXFJcNvpWiWUTZf6tf2V3wfa.jpg","Height":1049,"Iso_639_1":"en","Vote_Average":5.194,"Vote_Count":11,"Width":690},{"Aspect_Ratio":0.666666666666667,"File_Path":"/hal5bbB765hU8VAvvGrG51q461m.jpg","Height":1020,"Iso_639_1":"en","Vote_Average":5.18,"Vote_Count":3,"Width":680},{"Aspect_Ratio":0.708294930875576,"File_Path":"/Aa0pc78DbX9zww057mZZXrjBLkV.jpg","Height":2170,"Iso_639_1":"hu","Vote_Average":5.172,"Vote_Count":1,"Width":1537},{"Aspect_Ratio":0.68875,"File_Path":"/66ZFTV1Mh57aaWlMP0CvxdB686F.jpg","Height":1600,"Iso_639_1":"es","Vote_Average":5.172,"Vote_Count":1,"Width":1102},{"Aspect_Ratio":0.753183153770813,"File_Path":"/aDIlbtJLEBCtOAy1P9Y29D2QcYc.jpg","Height":1021,"Iso_639_1":"en","Vote_Average":5.172,"Vote_Count":1,"Width":769},{"Aspect_Ratio":0.688468158347676,"File_Path":"/xZv9kXd7AeF2BfECn8jW0M1WLl.jpg","Height":581,"Iso_639_1":"fr","Vote_Average":5.172,"Vote_Count":1,"Width":400},{"Aspect_Ratio":0.7125,"File_Path":"/2HsKQOYmRgpw9hzPmoAXHMNNZjI.jpg","Height":800,"Iso_639_1":"en","Vote_Average":5.106,"Vote_Count":2,"Width":570},{"Aspect_Ratio":1,"File_Path":"/vPNHt1NkcnzMnC7qz9W7UaWqSDW.jpg","Height":500,"Iso_639_1":"en","Vote_Average":4.922,"Vote_Count":5,"Width":500},{"Aspect_Ratio":0.666666666666667,"File_Path":"/csy93xPH0v74gFQvK0SRLGv6zXn.jpg","Height":1500,"Iso_639_1":"da","Vote_Average":0,"Vote_Count":0,"Width":1000},{"Aspect_Ratio":0.666666666666667,"File_Path":"/tURsjA0KUmlSpUvTkisQCt7ZST4.jpg","Height":750,"Iso_639_1":"fr","Vote_Average":0,"Vote_Count":0,"Width":500},{"Aspect_Ratio":0.706319702602231,"File_Path":"/mONe7xoOkh79DvPGosZUsnZ2w06.jpg","Height":807,"Iso_639_1":"pt","Vote_Average":0,"Vote_Count":0,"Width":570}]},"Keywords":{},"Trailers":{"Youtube":[]}}