{"Adult":false,"Backdrop_Path":"/3b7KBWUVoAN9sc90gvyZwX30cFV.jpg","Belongs_To_Collection":{"Id":12087,"Name":"Herbie Collection","Poster_Path":"/fD9IHehwlfRjZSUShCTcamxdfAP.jpg","Backdrop_Path":"/hgi9EeU50KFhv9pCDmJyx4VLp5G.jpg"},"Budget":0,"Genres":[{"Id":10749,"Name":"Romance"},{"Id":35,"Name":"Comedy"},{"Id":10751,"Name":"Family"},{"Id":14,"Name":"Fantasy"}],"Id":10869,"Imdb_Id":"tt0071607","Original_Title":"Herbie Rides Again","Overview":"The living Volkswagen Beetle helps an old lady protect her home from a corrupt developer.","Popularity":9.738,"Poster_Path":"/1zwUtG1kwpJGtVqidpOrarswUB0.jpg","Production_Companies":[{"Name":"Walt Disney Pictures","Id":2}],"Production_Countries":[{"Iso_3166_1":"US","Name":"United States of America"}],"Release_Date":"1974-02-14","Revenue":0,"Runtime":88,"Spoken_Languages":[{"Iso_639_1":"en","Name":"English"}],"Status":"Released","Tagline":"The Loveable Bug's back doin' his thing!","Title":"Herbie Rides Again","Vote_Average":5.9,"Vote_Count":167,"Casts":{"Cast":[{"Id":47439,"Name":"Helen Hayes","Character":"Mrs. Steinmetz","Order":0,"Cast_Id":1,"Profile_Path":"/6QJDTvIT0v5E9pR1rgPtq59Ej8.jpg"},{"Id":35031,"Name":"Ken Berry","Character":"Willoughby Whitfield","Order":1,"Cast_Id":2,"Profile_Path":"/i8fHfRK4668hqSxWfSEd1l6nh5Z.jpg"},{"Id":39762,"Name":"Stefanie Powers","Character":"Nicole Harris","Order":2,"Cast_Id":3,"Profile_Path":"/xjK7ytgxD9MVkB1vTgjHgn83xMS.jpg"},{"Id":53010,"Name":"John McIntire","Character":"Mr. Judson","Order":3,"Cast_Id":4,"Profile_Path":"/mqg5Cs6d6FCXlkR0ntUZfmR4As6.jpg"},{"Id":4966,"Name":"Keenan Wynn","Character":"Alonzo P Hawk","Order":4,"Cast_Id":13,"Profile_Path":"/vKRcpt50Eh9AQ6yi9umy1YFZWyf.jpg"},{"Id":88450,"Name":"Chuck McCann","Character":"Loostgarten","Order":5,"Cast_Id":14,"Profile_Path":"/vRsH2ZDfrrXe8ldfsUpd5qqTx2t.jpg"},{"Id":33024,"Name":"Huntz Hall","Character":"Judge","Order":6,"Cast_Id":20,"Profile_Path":"/wR3Rlmbwu5gfISwljC1Z0VRSvp4.jpg"},{"Id":1218966,"Name":"Ivor Barry","Character":"Chauffeur","Order":7,"Cast_Id":21},{"Id":85359,"Name":"Dan Tobin","Character":"Lawyer","Order":8,"Cast_Id":22,"Profile_Path":"/mAAhZpOk99PqmAZRdkZBKP0XxVy.jpg"},{"Id":82779,"Name":"Vito Scotti","Character":"Taxi Driver","Order":9,"Cast_Id":23,"Profile_Path":"/pN3aRdEF78xyCHsZrju56FO12wK.jpg"},{"Id":5737,"Name":"Raymond Bailey","Character":"Lawyer","Order":10,"Cast_Id":24,"Profile_Path":"/f27gMhRJhKdC99Ti2cloU7P5fLs.jpg"},{"Id":152711,"Name":"Liam Dunn","Character":"Doctor","Order":11,"Cast_Id":25,"Profile_Path":"/clIjX0wrNp7KyuqNvTG5Bo4O3xH.jpg"},{"Id":102753,"Name":"Elaine Devry","Character":"Secretary","Order":12,"Cast_Id":26,"Profile_Path":"/Cld7oBWutRz75eIO6ntuefdRTH.jpg"},{"Id":120105,"Name":"Richard X. Slattery","Character":"Traffic Commissioner","Order":13,"Cast_Id":27,"Profile_Path":"/vZR2CSmDf2HRQNhHxqidVRQf96L.jpg"},{"Id":1374832,"Name":"Hank Jones","Character":"Sir Lancelot","Order":14,"Cast_Id":28,"Profile_Path":"/kXmxVycgvSJfztC5ewVpRY9FAnF.jpg"},{"Id":101032,"Name":"Rod McCary","Character":"Red Knight","Order":15,"Cast_Id":29,"Profile_Path":"/kek1TqmBvMixBWweyKIPDNG1rZo.jpg"},{"Id":9222,"Name":"Don Pedro Colley","Character":"Barnstorff","Order":16,"Cast_Id":30,"Profile_Path":"/mNkseUBCrAESDKVTDdwWSEw6oUq.jpg"},{"Id":82750,"Name":"Larry J. Blake","Character":"Police Officer","Order":17,"Cast_Id":31,"Profile_Path":"/cDpE64sWON2AYpXPawPvUE2Kp9L.jpg"},{"Id":151628,"Name":"Iggie Wolfington","Character":"Lawyer - Second Team","Order":18,"Cast_Id":32},{"Id":180677,"Name":"Jack Manning","Character":"Lawyer - First Team","Order":19,"Cast_Id":33},{"Id":15781,"Name":"Hal Baylor","Character":"Demolition Truck Driver","Order":20,"Cast_Id":34,"Profile_Path":"/cb7gNKJNP861uzmGwUVRm0wfcXL.jpg"},{"Id":134614,"Name":"Herb Vigran","Character":"Window Washer","Order":21,"Cast_Id":35,"Profile_Path":"/wArAG67tnl4ph5HyHDnaNmL56Cr.jpg"},{"Id":165584,"Name":"James Almanzar","Character":"","Order":22,"Cast_Id":36,"Profile_Path":"/d5FNGIhPZVpE3559hS1lJRpnT2k.jpg"},{"Id":61676,"Name":"Candy Candido","Character":"","Order":23,"Cast_Id":37,"Profile_Path":"/5tjykiBmPIrnpPfHALfOqgEY7Nh.jpg"},{"Id":95013,"Name":"Edward Ashley","Character":"Announcer at Chicken Race","Order":24,"Cast_Id":38,"Profile_Path":"/Bs13GSDR3cjCSsrxKZFBojvFO5.jpg"},{"Id":1675496,"Name":"Norman Grabowski","Character":"Security Guard #2","Order":25,"Cast_Id":39,"Profile_Path":"/zdHg0RcNh9heTTu2ch5c7NBJCcF.jpg"},{"Id":70775,"Name":"Hal Williams","Character":"","Order":26,"Cast_Id":40,"Profile_Path":"/chgXhpx98cR5lV39hd43UF6QPZR.jpg"},{"Id":1406719,"Name":"Irwin Charone","Character":"Lawyer - Second Team","Order":27,"Cast_Id":41},{"Id":153263,"Name":"Gail Bonney","Character":"Rich Woman in Mansion","Order":28,"Cast_Id":42,"Profile_Path":"/wQlgK78rK8qLQqdeIVNDsx2NIW2.jpg"},{"Id":151522,"Name":"Burt Mustin","Character":"Rich Man in Mansion","Order":29,"Cast_Id":43,"Profile_Path":"/fXPom6V4uZlV6zsSAvghwj7kphC.jpg"},{"Id":108172,"Name":"John Myhers","Character":"Announcer at San Francisco's Office of the President","Order":30,"Cast_Id":44,"Profile_Path":"/buJ84g8FtK95dv5BkbfNB3nwZO0.jpg"},{"Id":15869,"Name":"John Stephenson","Character":"Lawyer - Second Team","Order":31,"Cast_Id":45,"Profile_Path":"/5atzhAYw83cax7bEgN22YGoEgu1.jpg"},{"Id":121209,"Name":"Robert Carson","Character":"Lawyer - First Team","Order":32,"Cast_Id":46},{"Id":34365,"Name":"Arthur Space","Character":"Beach Caretaker","Order":33,"Cast_Id":47,"Profile_Path":"/wZjrUXjfvoKL369xn5oMDGIg2wK.jpg"},{"Id":33230,"Name":"John Hubbard","Character":"Angry Chauffeur","Order":34,"Cast_Id":48,"Profile_Path":"/9zTAaXejiTGKEJfFIBUIhHo481t.jpg"},{"Id":13821,"Name":"Fritz Feld","Character":"Maitre d'","Order":35,"Cast_Id":49,"Profile_Path":"/kTS9wZWTKH61e3e7k2LQOuBIle8.jpg"},{"Id":40001,"Name":"Alvy Moore","Character":"Angry Taxi Driver","Order":36,"Cast_Id":50,"Profile_Path":"/9tRo3inSMsBBgk8t7UwZElxqXjP.jpg"},{"Id":153618,"Name":"Karl Lukas","Character":"Angry Construction Worker","Order":37,"Cast_Id":51},{"Id":166039,"Name":"Paul Micale","Character":"Fisherman's Wharf Waiter","Order":38,"Cast_Id":52,"Profile_Path":"/c6Fbn2Sz9Vd77U1fimgXsoYQeC6.jpg"},{"Id":82747,"Name":"John Zaremba","Character":"Lawyer - First Team","Order":39,"Cast_Id":53,"Profile_Path":"/AjH1gao2p6ZcuI6GwNm6H3f9j31.jpg"},{"Id":105804,"Name":"Alan Carney","Character":"Judge with Cigar at Chicken Run","Order":40,"Cast_Id":54,"Profile_Path":"/bupTMbL6qwYhclIhmCEv6lXyQyB.jpg"},{"Id":77482,"Name":"Ken Sansom","Character":"Lawyer - First Team","Order":41,"Cast_Id":55,"Profile_Path":"/el8Oje4diZsMZBk91q0xDOZH0Bq.jpg"},{"Id":122008,"Name":"Maurice Marsac","Character":"French Waiter","Order":42,"Cast_Id":56,"Profile_Path":"/kaURxtL9D9YEXVW7ZZSnTlcSKx5.jpg"},{"Id":153502,"Name":"Martin Braddock","Character":"","Order":43,"Cast_Id":57},{"Id":16978,"Name":"David Mooney","Character":"Young Man Surfing (uncredited)","Order":44,"Cast_Id":58},{"Id":27164,"Name":"Frank Baker","Character":"Man at Building Presentation (uncredited)","Order":45,"Cast_Id":59,"Profile_Path":"/fSYn9ESiVpuJtEuS67ttAGceEQW.jpg"},{"Id":1821525,"Name":"Alex Ball","Character":"Man at Building Presentation (uncredited)","Order":46,"Cast_Id":60},{"Id":1047407,"Name":"Spencer Chan","Character":"Man at Building Presentation (uncredited)","Order":47,"Cast_Id":61},{"Id":1240834,"Name":"Dorothy Konrad","Character":"Angry Woman in Crowd (uncredited)","Order":48,"Cast_Id":62},{"Id":1214019,"Name":"Joseph V. Perry","Character":"First Cab Driver (uncredited)","Order":49,"Cast_Id":63,"Profile_Path":"/lVz29eAxU8BXYdHFSCe8E7nXqZD.jpg"},{"Id":1212974,"Name":"Lomax Study","Character":"Waiter with Cake (uncredited)","Order":50,"Cast_Id":64}],"Crew":[{"Id":12869,"Credit_Id":"5af2a4f89251410676007355","Name":"John B. Mansbridge","Department":"Art","Job":"Art Direction"},{"Id":1261,"Credit_Id":"5af2a51c0e0a2668af0077dc","Name":"Hal Gausman","Department":"Art","Job":"Set Decoration"},{"Id":5834,"Credit_Id":"52fe43c79251416c7501dcd1","Name":"Robert Stevenson","Department":"Writing","Job":"Screenplay","Profile_Path":"/86MMwlxQ7AhJMn1JnDg8hjZbnSy.jpg"},{"Id":5834,"Credit_Id":"52fe43c79251416c7501dcdd","Name":"Robert Stevenson","Department":"Directing","Job":"Director","Profile_Path":"/86MMwlxQ7AhJMn1JnDg8hjZbnSy.jpg"},{"Id":5836,"Credit_Id":"52fe43c79251416c7501dce9","Name":"Bill Walsh","Department":"Production","Job":"Producer","Profile_Path":"/nfwyYYj1sVg5uneKLftutLhNqIN.jpg"},{"Id":5841,"Credit_Id":"52fe43c79251416c7501dce3","Name":"Cotton Warburton","Department":"Editing","Job":"Editor"},{"Id":10796,"Credit_Id":"5af2a551c3a36855cc00bc72","Name":"Robert J. Schiffer","Department":"Costume & Make-Up","Job":"Makeup Artist"},{"Id":21456,"Credit_Id":"5af2a50dc3a36855ac00a80e","Name":"Walter H. Tyler","Department":"Art","Job":"Art Direction"},{"Id":57337,"Credit_Id":"52fe43c79251416c7501dcf5","Name":"George Bruns","Department":"Sound","Job":"Music","Profile_Path":"/qH2a2m2LoLDCjpPj1h6sISFHDr0.jpg"},{"Id":58007,"Credit_Id":"52fe43c79251416c7501dcef","Name":"Frank V. Phillips","Department":"Camera","Job":"Director of Photography"},{"Id":62397,"Credit_Id":"52fe43c79251416c7501dcd7","Name":"Gordon Buford","Department":"Writing","Job":"Author"},{"Id":2022547,"Credit_Id":"5af2a53b0e0a26688e007cbc","Name":"La Rue Matheron","Department":"Costume & Make-Up","Job":"Hair Designer"},{"Id":2087193,"Credit_Id":"5b4fce92c3a368285800135e","Name":"Victor Roma","Department":"Production","Job":"Producer's Assistant","Profile_Path":"/rVp6KPPwq1HYvsM5waVSIKece5I.jpg"}]},"Releases":{"Countries":[{"Iso_3166_1":"BR","Certification":"","Release_Date":"1974-07-29T00:00:00.0000000Z"},{"Iso_3166_1":"DE","Certification":"6","Release_Date":"1974-10-10T00:00:00.0000000Z"},{"Iso_3166_1":"US","Certification":"G","Release_Date":"1974-02-14T00:00:00.0000000Z"},{"Iso_3166_1":"AU","Certification":"G","Release_Date":"1974-12-19T00:00:00.0000000Z"},{"Iso_3166_1":"GB","Certification":"U","Release_Date":"1974-02-15T00:00:00.0000000Z"},{"Iso_3166_1":"FR","Certification":"U","Release_Date":"1975-01-29T00:00:00.0000000Z"}]},"Images":{"Backdrops":[{"Aspect_Ratio":1.77777777777778,"File_Path":"/3b7KBWUVoAN9sc90gvyZwX30cFV.jpg","Height":720,"Iso_639_1":"en","Vote_Average":5.30505952380952,"Vote_Count":1,"Width":1280},{"Aspect_Ratio":1.77777777777778,"File_Path":"/rmzo0pwQi5pSFGYPEh98xkYqA5w.jpg","Height":1080,"Iso_639_1":"xx","Vote_Average":5.22344322344322,"Vote_Count":2,"Width":1920},{"Aspect_Ratio":1.77777777777778,"File_Path":"/d2LoYGl7VzfyuZn8868MsFjSIgj.jpg","Height":720,"Iso_639_1":"xx","Vote_Average":5.172,"Vote_Count":1,"Width":1280},{"Aspect_Ratio":1.76795580110497,"File_Path":"/zY31e2uL921aOrvechRwf7WXm0b.jpg","Height":724,"Iso_639_1":"xx","Vote_Average":5.128,"Vote_Count":2,"Width":1280},{"Aspect_Ratio":1.77777777777778,"File_Path":"/61i7OPpvvoDzzvXaKIRCGRD2lx0.jpg","Height":720,"Iso_639_1":"xx","Vote_Average":0,"Vote_Count":0,"Width":1280}],"Posters":[{"Aspect_Ratio":0.666666666666667,"File_Path":"/1zwUtG1kwpJGtVqidpOrarswUB0.jpg","Height":1500,"Iso_639_1":"en","Vote_Average":5.448,"Vote_Count":5,"Width":1000},{"Aspect_Ratio":0.666666666666667,"File_Path":"/90xgC9mlc6kYT1kzEYSSPcFGQmw.jpg","Height":3000,"Iso_639_1":"en","Vote_Average":5.246,"Vote_Count":2,"Width":2000},{"Aspect_Ratio":0.666666666666667,"File_Path":"/wGvHr04IcCkeSYFdkodVcKfTqKg.jpg","Height":1500,"Iso_639_1":"en","Vote_Average":5.172,"Vote_Count":1,"Width":1000},{"Aspect_Ratio":0.709333333333333,"File_Path":"/xLeJT2dpEFoIsNgf72z4J0YgzBo.jpg","Height":750,"Iso_639_1":"en","Vote_Average":5.106,"Vote_Count":2,"Width":532},{"Aspect_Ratio":0.704,"File_Path":"/p1jOHqEpElOHrK32ToayFHRczkO.jpg","Height":500,"Iso_639_1":"en","Vote_Average":5.106,"Vote_Count":2,"Width":352},{"Aspect_Ratio":0.654648956356736,"File_Path":"/7U37RClHIuneVXPIV0BaTrtNpI3.jpg","Height":1054,"Iso_639_1":"en","Vote_Average":5.01,"Vote_Count":4,"Width":690}]},"Keywords":{},"Trailers":{"Youtube":[{"Name":"Herbie Rides Again (1974) Disney Home Video Australia Trailer","Size":"HD","Source":"swDEaCgluWQ"}]}}